iacs/SVN
iacs/__init__.py
iacs/apps.py
iacs/log.py
iacs/mixins.py
iacs/models.py
iacs/permission.py
iacs/redis.py
iacs/swagger.py
iacs/urls.py
iacs/validators.py
iacs/websocket_messages.py
iacs/channels/__init__.py
iacs/channels/auth.py
iacs/channels/consumer.py
iacs/channels/notice.py
iacs/channels/server.py
iacs/channels/worker.py
iacs/channels/handlers/__init__.py
iacs/channels/handlers/snowflake.py
iacs/channels/handlers/user.py
iacs/channels/messages/__init__.py
iacs/channels/messages/exceptions.py
iacs/channels/messages/handler.py
iacs/channels/messages/messages.py
iacs/channels/messages/router.py
iacs/channels/messages/serializers.py
iacs/channels/messages/validators.py
iacs/filters/__init__.py
iacs/filters/operation_log.py
iacs/locale/zh_Hans/LC_MESSAGES/django.mo
iacs/locale/zh_Hans/LC_MESSAGES/django.po
iacs/management/__init__.py
iacs/management/commands/__init__.py
iacs/management/commands/iacs_collect_apis.py
iacs/management/commands/iacs_collect_menus.py
iacs/management/commands/initdatabase.py
iacs/migrations/0001_initial.py
iacs/migrations/__init__.py
iacs/rest/__init__.py
iacs/rest/auth.py
iacs/rest/decorator.py
iacs/rest/mixins.py
iacs/rest/pagination.py
iacs/rest/serializers.py
iacs/rest/viewsets.py
iacs/serializers/__init__.py
iacs/serializers/api.py
iacs/serializers/group.py
iacs/serializers/menu.py
iacs/serializers/operation_log.py
iacs/serializers/user.py
iacs/utils/__init__.py
iacs/utils/encryption.py
iacs/utils/file_handler.py
iacs/utils/snowflake.py
iacs/utils/time.py
iacs/viewsets/__init__.py
iacs/viewsets/api.py
iacs/viewsets/group.py
iacs/viewsets/menus.py
iacs/viewsets/operation_log.py
iacs/viewsets/users.py
django_iacs-2.0.3.dist-info/METADATA
django_iacs-2.0.3.dist-info/WHEEL
django_iacs-2.0.3.dist-info/top_level.txt
django_iacs-2.0.3.dist-info/RECORD
